foundation/__init__.py
foundation/radiant/__init__.py
foundation/radiant/server.py
foundation/radiant/template.html
foundation/radiant/utils.py
foundation/radiant/brython/foundation/__init__.py
foundation/radiant/brython/foundation/radiant/__init__.py
foundation/radiant/brython/foundation/radiant/figurestream.py
foundation/radiant/brython/foundation/radiant/server.py
foundation/radiant/brython/foundation/radiant/utils.py
foundation/radiant/python_tools/python_logger.py
foundation/radiant/python_tools/python_swarm.py
foundation/scripts/__init__.py
foundation/scripts/foundation_logs.py
foundation/scripts/foundation_status.py
foundation/scripts/foundation_worker.py
foundation/utils/__init__.py
foundation/utils/chaskilogs.py
foundation/utils/kafkalogs.py
foundation/utils/swarm.py
foundation/utils/workers.py
foundation/workers/__init__.py
foundation/workers/chaski2api/main.py
foundation/workers/chaski2api/requirements.txt
foundation/workers/chaski_api_logger/main.py
foundation/workers/chaski_api_logger/requirements.txt
foundation/workers/chaski_ca/main.py
foundation/workers/chaski_ca/requirements.txt
foundation/workers/chaski_logger_root/main.py
foundation/workers/chaski_logger_root/requirements.txt
foundation/workers/chaski_remote/main.py
foundation/workers/chaski_remote/requirements.txt
foundation/workers/chaski_root/main.py
foundation/workers/chaski_root/requirements.txt
foundation/workers/kafka2api/main.py
foundation/workers/main_app/main.py
foundation/workers/main_app/requirements.txt
foundation/workers/main_app/styles/styles.css
foundation/workers/main_app/templates/main_area.html
foundation/workers/timescaledb_api/db.sqlite3
foundation/workers/timescaledb_api/manage.py
foundation/workers/timescaledb_api/requirements.txt
foundation/workers/timescaledb_api/startup.sh
foundation/workers/timescaledb_api/djangoship/access.log
foundation/workers/timescaledb_api/djangoship/error.log
foundation/workers/timescaledb_api/resources/staticfiles.json
dunderlab_foundation-0.2.dist-info/LICENSE
dunderlab_foundation-0.2.dist-info/METADATA
dunderlab_foundation-0.2.dist-info/WHEEL
dunderlab_foundation-0.2.dist-info/entry_points.txt
dunderlab_foundation-0.2.dist-info/top_level.txt
dunderlab_foundation-0.2.dist-info/RECORD
